LICENSE
MANIFEST.in
README.txt
setup.py
src/oops_tools.egg-info/PKG-INFO
src/oops_tools.egg-info/SOURCES.txt
src/oops_tools.egg-info/dependency_links.txt
src/oops_tools.egg-info/entry_points.txt
src/oops_tools.egg-info/namespace_packages.txt
src/oops_tools.egg-info/not-zip-safe
src/oops_tools.egg-info/requires.txt
src/oops_tools.egg-info/top_level.txt
src/oopstools/__init__.py
src/oopstools/settings.py
src/oopstools/urls.py
src/oopstools/oops/__init__.py
src/oopstools/oops/admin.py
src/oopstools/oops/dboopsloader.py
src/oopstools/oops/dbsummaries.py
src/oopstools/oops/djangobrowser.py
src/oopstools/oops/helpers.py
src/oopstools/oops/log.py
src/oopstools/oops/models.py
src/oopstools/oops/oopsgroup.py
src/oopstools/oops/oopsstore.py
src/oopstools/oops/prefixloader.py
src/oopstools/oops/sections.py
src/oopstools/oops/summaries.py
src/oopstools/oops/views.py
src/oopstools/oops/migrations/0001_add_custom_group_concat_sql.py
src/oopstools/oops/migrations/0002_initial.py
src/oopstools/oops/migrations/0007_initial_appinstances.py
src/oopstools/oops/migrations/0008_initial_prefixes.py
src/oopstools/oops/migrations/0011_initial_classifications.py
src/oopstools/oops/migrations/0014_auto__add_prefixgroup__add_field_prefix_group.py
src/oopstools/oops/migrations/0016_auto__del_prefixgroup__add_report__del_field_prefix_group.py
src/oopstools/oops/migrations/0017_prefix_group_to_report.py
src/oopstools/oops/migrations/0020_add_oops_prune.py
src/oopstools/oops/migrations/0021_longer_reporter.py
src/oopstools/oops/migrations/0022_report_email_address.py
src/oopstools/oops/migrations/__init__.py
src/oopstools/oops/templatetags/__init__.py
src/oopstools/oops/templatetags/oops_extras.py
src/oopstools/oops/test/__init__.py
src/oopstools/oops/test/fakes.py
src/oopstools/oops/test/test_amqp2disk.py
src/oopstools/oops/test/test_dboopsloader.py
src/oopstools/oops/test/test_dbsummaries.py
src/oopstools/oops/test/test_runner.py
src/oopstools/scripts/__init__.py
src/oopstools/scripts/amqp2disk.py
src/oopstools/scripts/analyse_error_reports.py
src/oopstools/scripts/dir_finder.py
src/oopstools/scripts/graph_report.py
src/oopstools/scripts/load_sample_data.py
src/oopstools/scripts/prune.py
src/oopstools/scripts/report.py
src/oopstools/scripts/update_db.py