Metadata-Version: 1.1
Name: oops-tools
Version: 0.6.3
Summary: =================
Home-page: UNKNOWN
Author: Launchpad Developers
Author-email: launchpad-dev@lists.launchpad.net
License: UNKNOWN
Platform: UNKNOWN
Classifier: Development Status :: 5 - Production/Stable
Classifier: Intended Audience :: Developers
Classifier: License :: OSI Approved :: GNU Affero General Public License v3
Classifier: Operating System :: OS Independent
Classifier: Programming Language :: Python
